radoncfun.cpython-36m-darwin.so
pyradon/__init__.py
pyradon/pcg.py
pyradon/radon_inversion.py
pyradon/radon_op.py
pyradon-0.0.2.dist-info/METADATA
pyradon-0.0.2.dist-info/WHEEL
pyradon-0.0.2.dist-info/top_level.txt
pyradon-0.0.2.dist-info/RECORD
