Metadata-Version: 2.1
Name: pyradon
Version: 0.0.2
Summary: A python package of Radon transform for denoising and interpolation of multi-channel seismic data
Home-page: https://github.com/QuanZhang97/pyradon
Author: pyradon developing team
Author-email: quanzhang1997@gmail.com
License: GNU General Public License, Version 3 (GPLv3)
Keywords: seismology,earthquake seismology,exploration seismology,array seismology,denoising,science,engineering,structure,local slope,filtering
Platform: UNKNOWN
Classifier: Development Status :: 4 - Beta
Classifier: Intended Audience :: Developers
Classifier: Intended Audience :: Science/Research
Classifier: Operating System :: Unix
Classifier: Operating System :: POSIX
Classifier: Operating System :: Microsoft :: Windows
Classifier: Programming Language :: Python
Classifier: Programming Language :: Python :: 3.8
Classifier: Programming Language :: Python :: Implementation :: CPython
Classifier: Topic :: Scientific/Engineering
Classifier: Topic :: Scientific/Engineering :: Physics
Classifier: License :: OSI Approved :: GNU General Public License v3 (GPLv3)
Requires-Dist: numpy
Requires-Dist: scipy
Requires-Dist: matplotlib
Provides-Extra: docs
Requires-Dist: sphinx ; extra == 'docs'
Requires-Dist: ipython ; extra == 'docs'
Requires-Dist: runipy ; extra == 'docs'
